{
"companyName": "DefaultCompany",
"productName": "WWF",
"productVersion": "0.1",
"dataUrl": "Game10.data.unityweb",
"wasmCodeUrl": "Game10.wasm.code.unityweb",
"wasmFrameworkUrl": "Game10.wasm.framework.unityweb",
"graphicsAPI": ["WebGL 2.0","WebGL 1.0"],
"webglContextAttributes": {"preserveDrawingBuffer": false},
"splashScreenStyle": "Light",
"backgroundColor": "#FFFFFF",
"cacheControl": {"default": "must-revalidate"},
"developmentBuild": false,
"multithreading": false,
"unityVersion": "2019.3.12f1"
}